{
	"type": "FeatureCollection",
	"features": [
		{
			"type": "Feature",
			"geometry": {
				"type": "Point",
				"coordinates": [-71.27323518888062, 42.31222541339845]
			},
			"properties": {
				"clue": "Look for two stone birds",
				"sitename": "Looper Hu Household",
				"refShort": "18 Eaton Court",
				"time": "5-9pm"
			}
		},
		{
			"type": "Feature",
			"geometry": {
				"type": "Point",
				"coordinates": [-71.2834818, 42.3126688]
			},
			"properties": {
				"clue": "Look for the haunted archway",
				"sitename": "Agush Household",
				"refShort": "41 Sawyer Road",
				"time": "6-9pm"
			}
		},
		{
			"type": "Feature",
			"geometry": {
				"type": "Point",
				"coordinates": [-71.2885, 42.29786]
			},
			"properties": {
				"clue": "Look at that - under the bat!",
				"sitename": "Antonelli Household",
				"refShort": "10 Wellesley Ave",
				"time": "4-7pm"
			}
		}
	]
}
